yuan/__init__.py
yuanni-0.0.0.dist-info/LICENSE
yuanni-0.0.0.dist-info/METADATA
yuanni-0.0.0.dist-info/WHEEL
yuanni-0.0.0.dist-info/top_level.txt
yuanni-0.0.0.dist-info/RECORD
